{
	"@context": {
		"rdf": "http://www.w3.org/1999/02/22-rdf-syntax-ns#",
		"dct": "http://purl.org/dc/terms/",
		"owl": "http://www.w3.org/2002/07/owl#",
		"xsd": "http://www.w3.org/2001/XMLSchema#",
		"rdfs": "http://www.w3.org/2000/01/rdf-schema#",
		"@vocab": "http://ld.nice.org.uk/ns/bnf#",
		"bnf": "http://ld.nice.org.uk/ns/bnf/",
		"nicebnf": "http://ld.nice.org.uk/ns/bnf#",
		"route": "http://ld.nice.org.uk/ns/bnf/Route#",
		"patientGroup": "http://ld.nice.org.uk/ns/bnf/PatientGroup#",
		"indication": "http://ld.nice.org.uk/ns/bnf/Indication#",
		"sideEffect": "http://ld.nice.org.uk/ns/bnf/SideEffect#",
		"classification": "http://ld.nice.org.uk/ns/bnf/Classification#",
		"isLinkedFrom": {
			"@container": "@set"
		},
		"hasInteraction": {
			"@container": "@set"
		},
		"hasMessage": {
			"@container": "@set"
		},
		"hasInteractionList": {
			"@container": "@set"
		},
		"isInteractionListOf": {
			"@container": "@set"
		}
	},
	"@graph": [
		{
			"@id": "http://bnf.nice.org.uk/interaction/reboxetine-2",
			"@type": "InteractionList",
			"hasInteraction": [
				{
					"@id": "http://bnf.nice.org.uk/interaction/reboxetine-2#bnf_i1643858009508",
					"hasMessage": [
						{
							"@id": "http://bnf.nice.org.uk/interaction/reboxetine-2#bnf_i1643858009508_message_0",
							"hasDitaContent": {
								"@type": "rdf:XMLLiteral",
								"@value": "<p otherprops=\"Moderate\" outputclass=\"int-message\">\n  <ph otherprops=\"apalutamide\" outputclass=\"int-drug\">Apalutamide</ph> <ph outputclass=\"int-effectQualifier\">is predicted to</ph> <ph outputclass=\"int-effect\">decrease</ph> <ph outputclass=\"int-parameter\">the exposure to</ph> <ph otherprops=\"reboxetine\" outputclass=\"int-heading-drug\">reboxetine</ph>. <ph outputclass=\"int-action\">Manufacturer makes no recommendation</ph>.  </p>"
							},
							"hasEvidence": "Anecdotal",
							"hasImportance": "Moderate",
							"hasOrder": "1",
							"hasTextContent": "Apalutamide   is predicted to   decrease   the exposure to   reboxetine .  Manufacturer makes no recommendation .    \n\n"
						}
					],
					"hasOrder": "1",
					"hasTitle": {
						"@type": "rdf:XMLLiteral",
						"@value": "<title>Apalutamide</title>"
					}
				},
				{
					"@id": "http://bnf.nice.org.uk/interaction/reboxetine-2#bnf_i1643858009509",
					"hasMessage": [
						{
							"@id": "http://bnf.nice.org.uk/interaction/reboxetine-2#bnf_i1643858009509_message_0",
							"hasDitaContent": {
								"@type": "rdf:XMLLiteral",
								"@value": "<p otherprops=\"Moderate\" outputclass=\"int-message\">\n  <ph otherprops=\"atazanavir\" outputclass=\"int-drug\">Atazanavir</ph> <ph outputclass=\"int-effectQualifier\">is predicted to</ph> <ph outputclass=\"int-effect\">increase</ph> <ph outputclass=\"int-parameter\">the exposure to</ph> <ph otherprops=\"reboxetine\" outputclass=\"int-heading-drug\">reboxetine</ph>. <ph outputclass=\"int-action\">Manufacturer advises avoid</ph>.  </p>"
							},
							"hasEvidence": "Study",
							"hasImportance": "Moderate",
							"hasOrder": "1",
							"hasTextContent": "Atazanavir   is predicted to   increase   the exposure to   reboxetine .  Manufacturer advises avoid .    \n\n"
						}
					],
					"hasOrder": "2",
					"hasTitle": {
						"@type": "rdf:XMLLiteral",
						"@value": "<title>Atazanavir</title>"
					}
				},
				{
					"@id": "http://bnf.nice.org.uk/interaction/reboxetine-2#bnf_i1643858009510",
					"hasMessage": [
						{
							"@id": "http://bnf.nice.org.uk/interaction/reboxetine-2#bnf_i1643858009510_message_0",
							"hasDitaContent": {
								"@type": "rdf:XMLLiteral",
								"@value": "<p otherprops=\"Moderate\" outputclass=\"int-message\">\n  <ph otherprops=\"reboxetine\" outputclass=\"int-heading-drug\">Reboxetine</ph> <ph outputclass=\"int-effectQualifier\">is predicted to</ph> <ph outputclass=\"int-effect\">increase</ph> <ph outputclass=\"int-parameter\">the risk of hypokalaemia when given with</ph> <ph otherprops=\"bendroflumethiazide\" outputclass=\"int-drug\">bendroflumethiazide</ph>. <ph outputclass=\"int-action\">Manufacturer makes no recommendation</ph>.  </p>"
							},
							"hasEvidence": "Anecdotal",
							"hasImportance": "Moderate",
							"hasOrder": "1",
							"hasTextContent": "Reboxetine   is predicted to   increase   the risk of hypokalaemia when given with   bendroflumethiazide .  Manufacturer makes no recommendation .    \n\n"
						}
					],
					"hasOrder": "3",
					"hasTitle": {
						"@type": "rdf:XMLLiteral",
						"@value": "<title>Bendroflumethiazide</title>"
					}
				},
				{
					"@id": "http://bnf.nice.org.uk/interaction/reboxetine-2#bnf_i1643858009511",
					"hasMessage": [
						{
							"@id": "http://bnf.nice.org.uk/interaction/reboxetine-2#bnf_i1643858009511_message_0",
							"hasDitaContent": {
								"@type": "rdf:XMLLiteral",
								"@value": "<p otherprops=\"Moderate\" outputclass=\"int-message\">\n  <ph otherprops=\"reboxetine\" outputclass=\"int-heading-drug\">Reboxetine</ph> <ph outputclass=\"int-effectQualifier\">is predicted to</ph> <ph outputclass=\"int-effect\">increase</ph> <ph outputclass=\"int-parameter\">the risk of hypokalaemia when given with</ph> <ph otherprops=\"bumetanide\" outputclass=\"int-drug\">bumetanide</ph>. <ph outputclass=\"int-action\">Manufacturer makes no recommendation</ph>.  </p>"
							},
							"hasEvidence": "Theoretical",
							"hasImportance": "Moderate",
							"hasOrder": "1",
							"hasTextContent": "Reboxetine   is predicted to   increase   the risk of hypokalaemia when given with   bumetanide .  Manufacturer makes no recommendation .    \n\n"
						}
					],
					"hasOrder": "4",
					"hasTitle": {
						"@type": "rdf:XMLLiteral",
						"@value": "<title>Bumetanide</title>"
					}
				},
				{
					"@id": "http://bnf.nice.org.uk/interaction/reboxetine-2#bnf_i1643858009512",
					"hasMessage": [
						{
							"@id": "http://bnf.nice.org.uk/interaction/reboxetine-2#bnf_i1643858009512_message_0",
							"hasDitaContent": {
								"@type": "rdf:XMLLiteral",
								"@value": "<p otherprops=\"Moderate\" outputclass=\"int-message\">\n  <ph otherprops=\"carbamazepine\" outputclass=\"int-drug\">Carbamazepine</ph> <ph outputclass=\"int-effectQualifier\">is predicted to</ph> <ph outputclass=\"int-effect\">decrease</ph> <ph outputclass=\"int-parameter\">the exposure to</ph> <ph otherprops=\"reboxetine\" outputclass=\"int-heading-drug\">reboxetine</ph>. <ph outputclass=\"int-action\">Manufacturer makes no recommendation</ph>.  </p>"
							},
							"hasEvidence": "Anecdotal",
							"hasImportance": "Moderate",
							"hasOrder": "1",
							"hasTextContent": "Carbamazepine   is predicted to   decrease   the exposure to   reboxetine .  Manufacturer makes no recommendation .    \n\n"
						}
					],
					"hasOrder": "5",
					"hasTitle": {
						"@type": "rdf:XMLLiteral",
						"@value": "<title>Carbamazepine</title>"
					}
				},
				{
					"@id": "http://bnf.nice.org.uk/interaction/reboxetine-2#bnf_i1643858009513",
					"hasMessage": [
						{
							"@id": "http://bnf.nice.org.uk/interaction/reboxetine-2#bnf_i1643858009513_message_0",
							"hasDitaContent": {
								"@type": "rdf:XMLLiteral",
								"@value": "<p otherprops=\"Moderate\" outputclass=\"int-message\">\n  <ph otherprops=\"reboxetine\" outputclass=\"int-heading-drug\">Reboxetine</ph> <ph outputclass=\"int-effectQualifier\">is predicted to</ph> <ph outputclass=\"int-effect\">increase</ph> <ph outputclass=\"int-parameter\">the risk of hypokalaemia when given with</ph> <ph otherprops=\"chlorothiazide\" outputclass=\"int-drug\">chlorothiazide</ph>. <ph outputclass=\"int-action\">Manufacturer makes no recommendation</ph>.  </p>"
							},
							"hasEvidence": "Anecdotal",
							"hasImportance": "Moderate",
							"hasOrder": "1",
							"hasTextContent": "Reboxetine   is predicted to   increase   the risk of hypokalaemia when given with   chlorothiazide .  Manufacturer makes no recommendation .    \n\n"
						}
					],
					"hasOrder": "6",
					"hasTitle": {
						"@type": "rdf:XMLLiteral",
						"@value": "<title>Chlorothiazide</title>"
					}
				},
				{
					"@id": "http://bnf.nice.org.uk/interaction/reboxetine-2#bnf_i1643858009514",
					"hasMessage": [
						{
							"@id": "http://bnf.nice.org.uk/interaction/reboxetine-2#bnf_i1643858009514_message_0",
							"hasDitaContent": {
								"@type": "rdf:XMLLiteral",
								"@value": "<p otherprops=\"Moderate\" outputclass=\"int-message\">\n  <ph otherprops=\"reboxetine\" outputclass=\"int-heading-drug\">Reboxetine</ph> <ph outputclass=\"int-effectQualifier\">is predicted to</ph> <ph outputclass=\"int-effect\">increase</ph> <ph outputclass=\"int-parameter\">the risk of hypokalaemia when given with</ph> <ph otherprops=\"chlortalidone\" outputclass=\"int-drug\">chlortalidone</ph>. <ph outputclass=\"int-action\">Manufacturer makes no recommendation</ph>.  </p>"
							},
							"hasEvidence": "Anecdotal",
							"hasImportance": "Moderate",
							"hasOrder": "1",
							"hasTextContent": "Reboxetine   is predicted to   increase   the risk of hypokalaemia when given with   chlortalidone .  Manufacturer makes no recommendation .    \n\n"
						}
					],
					"hasOrder": "7",
					"hasTitle": {
						"@type": "rdf:XMLLiteral",
						"@value": "<title>Chlortalidone</title>"
					}
				},
				{
					"@id": "http://bnf.nice.org.uk/interaction/reboxetine-2#bnf_i1643858009515",
					"hasMessage": [
						{
							"@id": "http://bnf.nice.org.uk/interaction/reboxetine-2#bnf_i1643858009515_message_0",
							"hasDitaContent": {
								"@type": "rdf:XMLLiteral",
								"@value": "<p otherprops=\"Moderate\" outputclass=\"int-message\">\n  <ph otherprops=\"clarithromycin\" outputclass=\"int-drug\">Clarithromycin</ph> <ph outputclass=\"int-effectQualifier\">is predicted to</ph> <ph outputclass=\"int-effect\">increase</ph> <ph outputclass=\"int-parameter\">the exposure to</ph> <ph otherprops=\"reboxetine\" outputclass=\"int-heading-drug\">reboxetine</ph>. <ph outputclass=\"int-action\">Manufacturer advises avoid</ph>.  </p>"
							},
							"hasEvidence": "Study",
							"hasImportance": "Moderate",
							"hasOrder": "1",
							"hasTextContent": "Clarithromycin   is predicted to   increase   the exposure to   reboxetine .  Manufacturer advises avoid .    \n\n"
						}
					],
					"hasOrder": "8",
					"hasTitle": {
						"@type": "rdf:XMLLiteral",
						"@value": "<title>Clarithromycin</title>"
					}
				},
				{
					"@id": "http://bnf.nice.org.uk/interaction/reboxetine-2#bnf_i1643858009516",
					"hasMessage": [
						{
							"@id": "http://bnf.nice.org.uk/interaction/reboxetine-2#bnf_i1643858009516_message_0",
							"hasDitaContent": {
								"@type": "rdf:XMLLiteral",
								"@value": "<p otherprops=\"Moderate\" outputclass=\"int-message\">\n  <ph otherprops=\"cobicistat\" outputclass=\"int-drug\">Cobicistat</ph> <ph outputclass=\"int-effectQualifier\">is predicted to</ph> <ph outputclass=\"int-effect\">increase</ph> <ph outputclass=\"int-parameter\">the exposure to</ph> <ph otherprops=\"reboxetine\" outputclass=\"int-heading-drug\">reboxetine</ph>. <ph outputclass=\"int-action\">Manufacturer advises avoid</ph>.  </p>"
							},
							"hasEvidence": "Study",
							"hasImportance": "Moderate",
							"hasOrder": "1",
							"hasTextContent": "Cobicistat   is predicted to   increase   the exposure to   reboxetine .  Manufacturer advises avoid .    \n\n"
						}
					],
					"hasOrder": "9",
					"hasTitle": {
						"@type": "rdf:XMLLiteral",
						"@value": "<title>Cobicistat</title>"
					}
				},
				{
					"@id": "http://bnf.nice.org.uk/interaction/reboxetine-2#bnf_i1643858009517",
					"hasMessage": [
						{
							"@id": "http://bnf.nice.org.uk/interaction/reboxetine-2#bnf_i1643858009517_message_0",
							"hasDitaContent": {
								"@type": "rdf:XMLLiteral",
								"@value": "<p otherprops=\"Moderate\" outputclass=\"int-message\">\n  <ph otherprops=\"darunavir\" outputclass=\"int-drug\">Darunavir</ph> <ph outputclass=\"int-effectQualifier\">is predicted to</ph> <ph outputclass=\"int-effect\">increase</ph> <ph outputclass=\"int-parameter\">the exposure to</ph> <ph otherprops=\"reboxetine\" outputclass=\"int-heading-drug\">reboxetine</ph>. <ph outputclass=\"int-action\">Manufacturer advises avoid</ph>.  </p>"
							},
							"hasEvidence": "Study",
							"hasImportance": "Moderate",
							"hasOrder": "1",
							"hasTextContent": "Darunavir   is predicted to   increase   the exposure to   reboxetine .  Manufacturer advises avoid .    \n\n"
						}
					],
					"hasOrder": "10",
					"hasTitle": {
						"@type": "rdf:XMLLiteral",
						"@value": "<title>Darunavir</title>"
					}
				},
				{
					"@id": "http://bnf.nice.org.uk/interaction/reboxetine-2#bnf_i1643858009518",
					"hasMessage": [
						{
							"@id": "http://bnf.nice.org.uk/interaction/reboxetine-2#bnf_i1643858009518_message_0",
							"hasDitaContent": {
								"@type": "rdf:XMLLiteral",
								"@value": "<p otherprops=\"Moderate\" outputclass=\"int-message\">\n  <ph otherprops=\"enzalutamide\" outputclass=\"int-drug\">Enzalutamide</ph> <ph outputclass=\"int-effectQualifier\">is predicted to</ph> <ph outputclass=\"int-effect\">decrease</ph> <ph outputclass=\"int-parameter\">the exposure to</ph> <ph otherprops=\"reboxetine\" outputclass=\"int-heading-drug\">reboxetine</ph>. <ph outputclass=\"int-action\">Manufacturer makes no recommendation</ph>.  </p>"
							},
							"hasEvidence": "Anecdotal",
							"hasImportance": "Moderate",
							"hasOrder": "1",
							"hasTextContent": "Enzalutamide   is predicted to   decrease   the exposure to   reboxetine .  Manufacturer makes no recommendation .    \n\n"
						}
					],
					"hasOrder": "11",
					"hasTitle": {
						"@type": "rdf:XMLLiteral",
						"@value": "<title>Enzalutamide</title>"
					}
				},
				{
					"@id": "http://bnf.nice.org.uk/interaction/reboxetine-2#bnf_i1643858009519",
					"hasMessage": [
						{
							"@id": "http://bnf.nice.org.uk/interaction/reboxetine-2#bnf_i1643858009519_message_0",
							"hasDitaContent": {
								"@type": "rdf:XMLLiteral",
								"@value": "<p otherprops=\"Moderate\" outputclass=\"int-message\">\n  <ph otherprops=\"fosamprenavir\" outputclass=\"int-drug\">Fosamprenavir</ph> <ph outputclass=\"int-effectQualifier\">is predicted to</ph> <ph outputclass=\"int-effect\">increase</ph> <ph outputclass=\"int-parameter\">the exposure to</ph> <ph otherprops=\"reboxetine\" outputclass=\"int-heading-drug\">reboxetine</ph>. <ph outputclass=\"int-action\">Manufacturer advises avoid</ph>.  </p>"
							},
							"hasEvidence": "Study",
							"hasImportance": "Moderate",
							"hasOrder": "1",
							"hasTextContent": "Fosamprenavir   is predicted to   increase   the exposure to   reboxetine .  Manufacturer advises avoid .    \n\n"
						}
					],
					"hasOrder": "12",
					"hasTitle": {
						"@type": "rdf:XMLLiteral",
						"@value": "<title>Fosamprenavir</title>"
					}
				},
				{
					"@id": "http://bnf.nice.org.uk/interaction/reboxetine-2#bnf_i1643858009520",
					"hasMessage": [
						{
							"@id": "http://bnf.nice.org.uk/interaction/reboxetine-2#bnf_i1643858009520_message_0",
							"hasDitaContent": {
								"@type": "rdf:XMLLiteral",
								"@value": "<p otherprops=\"Moderate\" outputclass=\"int-message\">\n  <ph otherprops=\"fosphenytoin\" outputclass=\"int-drug\">Fosphenytoin</ph> <ph outputclass=\"int-effectQualifier\">is predicted to</ph> <ph outputclass=\"int-effect\">decrease</ph> <ph outputclass=\"int-parameter\">the exposure to</ph> <ph otherprops=\"reboxetine\" outputclass=\"int-heading-drug\">reboxetine</ph>. <ph outputclass=\"int-action\">Manufacturer makes no recommendation</ph>.  </p>"
							},
							"hasEvidence": "Anecdotal",
							"hasImportance": "Moderate",
							"hasOrder": "1",
							"hasTextContent": "Fosphenytoin   is predicted to   decrease   the exposure to   reboxetine .  Manufacturer makes no recommendation .    \n\n"
						}
					],
					"hasOrder": "13",
					"hasTitle": {
						"@type": "rdf:XMLLiteral",
						"@value": "<title>Fosphenytoin</title>"
					}
				},
				{
					"@id": "http://bnf.nice.org.uk/interaction/reboxetine-2#bnf_i1643858009521",
					"hasMessage": [
						{
							"@id": "http://bnf.nice.org.uk/interaction/reboxetine-2#bnf_i1643858009521_message_0",
							"hasDitaContent": {
								"@type": "rdf:XMLLiteral",
								"@value": "<p otherprops=\"Moderate\" outputclass=\"int-message\">\n  <ph otherprops=\"reboxetine\" outputclass=\"int-heading-drug\">Reboxetine</ph> <ph outputclass=\"int-effectQualifier\">is predicted to</ph> <ph outputclass=\"int-effect\">increase</ph> <ph outputclass=\"int-parameter\">the risk of hypokalaemia when given with</ph> <ph otherprops=\"furosemide\" outputclass=\"int-drug\">furosemide</ph>. <ph outputclass=\"int-action\">Manufacturer makes no recommendation</ph>.  </p>"
							},
							"hasEvidence": "Theoretical",
							"hasImportance": "Moderate",
							"hasOrder": "1",
							"hasTextContent": "Reboxetine   is predicted to   increase   the risk of hypokalaemia when given with   furosemide .  Manufacturer makes no recommendation .    \n\n"
						}
					],
					"hasOrder": "14",
					"hasTitle": {
						"@type": "rdf:XMLLiteral",
						"@value": "<title>Furosemide</title>"
					}
				},
				{
					"@id": "http://bnf.nice.org.uk/interaction/reboxetine-2#bnf_i1643858009522",
					"hasMessage": [
						{
							"@id": "http://bnf.nice.org.uk/interaction/reboxetine-2#bnf_i1643858009522_message_0",
							"hasDitaContent": {
								"@type": "rdf:XMLLiteral",
								"@value": "<p otherprops=\"Moderate\" outputclass=\"int-message\">\n  <ph otherprops=\"reboxetine\" outputclass=\"int-heading-drug\">Reboxetine</ph> <ph outputclass=\"int-effectQualifier\">is predicted to</ph> <ph outputclass=\"int-effect\">increase</ph> <ph outputclass=\"int-parameter\">the risk of hypokalaemia when given with</ph> <ph otherprops=\"hydrochlorothiazide\" outputclass=\"int-drug\">hydrochlorothiazide</ph>. <ph outputclass=\"int-action\">Manufacturer makes no recommendation</ph>.  </p>"
							},
							"hasEvidence": "Anecdotal",
							"hasImportance": "Moderate",
							"hasOrder": "1",
							"hasTextContent": "Reboxetine   is predicted to   increase   the risk of hypokalaemia when given with   hydrochlorothiazide .  Manufacturer makes no recommendation .    \n\n"
						}
					],
					"hasOrder": "15",
					"hasTitle": {
						"@type": "rdf:XMLLiteral",
						"@value": "<title>Hydrochlorothiazide</title>"
					}
				},
				{
					"@id": "http://bnf.nice.org.uk/interaction/reboxetine-2#bnf_i1643858009523",
					"hasMessage": [
						{
							"@id": "http://bnf.nice.org.uk/interaction/reboxetine-2#bnf_i1643858009523_message_0",
							"hasDitaContent": {
								"@type": "rdf:XMLLiteral",
								"@value": "<p otherprops=\"Moderate\" outputclass=\"int-message\">\n  <ph otherprops=\"reboxetine\" outputclass=\"int-heading-drug\">Reboxetine</ph> <ph outputclass=\"int-effectQualifier\">is predicted to</ph> <ph outputclass=\"int-effect\">increase</ph> <ph outputclass=\"int-parameter\">the risk of hypokalaemia when given with</ph> <ph otherprops=\"hydroflumethiazide\" outputclass=\"int-drug\">hydroflumethiazide</ph>. <ph outputclass=\"int-action\">Manufacturer makes no recommendation</ph>.  </p>"
							},
							"hasEvidence": "Anecdotal",
							"hasImportance": "Moderate",
							"hasOrder": "1",
							"hasTextContent": "Reboxetine   is predicted to   increase   the risk of hypokalaemia when given with   hydroflumethiazide .  Manufacturer makes no recommendation .    \n\n"
						}
					],
					"hasOrder": "16",
					"hasTitle": {
						"@type": "rdf:XMLLiteral",
						"@value": "<title>Hydroflumethiazide</title>"
					}
				},
				{
					"@id": "http://bnf.nice.org.uk/interaction/reboxetine-2#bnf_i1643858009524",
					"hasMessage": [
						{
							"@id": "http://bnf.nice.org.uk/interaction/reboxetine-2#bnf_i1643858009524_message_0",
							"hasDitaContent": {
								"@type": "rdf:XMLLiteral",
								"@value": "<p otherprops=\"Moderate\" outputclass=\"int-message\">\n  <ph otherprops=\"idelalisib\" outputclass=\"int-drug\">Idelalisib</ph> <ph outputclass=\"int-effectQualifier\">is predicted to</ph> <ph outputclass=\"int-effect\">increase</ph> <ph outputclass=\"int-parameter\">the exposure to</ph> <ph otherprops=\"reboxetine\" outputclass=\"int-heading-drug\">reboxetine</ph>. <ph outputclass=\"int-action\">Manufacturer advises avoid</ph>.  </p>"
							},
							"hasEvidence": "Study",
							"hasImportance": "Moderate",
							"hasOrder": "1",
							"hasTextContent": "Idelalisib   is predicted to   increase   the exposure to   reboxetine .  Manufacturer advises avoid .    \n\n"
						}
					],
					"hasOrder": "17",
					"hasTitle": {
						"@type": "rdf:XMLLiteral",
						"@value": "<title>Idelalisib</title>"
					}
				},
				{
					"@id": "http://bnf.nice.org.uk/interaction/reboxetine-2#bnf_i1643858009525",
					"hasMessage": [
						{
							"@id": "http://bnf.nice.org.uk/interaction/reboxetine-2#bnf_i1643858009525_message_0",
							"hasDitaContent": {
								"@type": "rdf:XMLLiteral",
								"@value": "<p otherprops=\"Moderate\" outputclass=\"int-message\">\n  <ph otherprops=\"reboxetine\" outputclass=\"int-heading-drug\">Reboxetine</ph> <ph outputclass=\"int-effectQualifier\">is predicted to</ph> <ph outputclass=\"int-effect\">increase</ph> <ph outputclass=\"int-parameter\">the risk of hypokalaemia when given with</ph> <ph otherprops=\"indapamide\" outputclass=\"int-drug\">indapamide</ph>. <ph outputclass=\"int-action\">Manufacturer makes no recommendation</ph>.  </p>"
							},
							"hasEvidence": "Anecdotal",
							"hasImportance": "Moderate",
							"hasOrder": "1",
							"hasTextContent": "Reboxetine   is predicted to   increase   the risk of hypokalaemia when given with   indapamide .  Manufacturer makes no recommendation .    \n\n"
						}
					],
					"hasOrder": "18",
					"hasTitle": {
						"@type": "rdf:XMLLiteral",
						"@value": "<title>Indapamide</title>"
					}
				},
				{
					"@id": "http://bnf.nice.org.uk/interaction/reboxetine-2#bnf_i1643858009526",
					"hasMessage": [
						{
							"@id": "http://bnf.nice.org.uk/interaction/reboxetine-2#bnf_i1643858009526_message_0",
							"hasDitaContent": {
								"@type": "rdf:XMLLiteral",
								"@value": "<p otherprops=\"Severe\" outputclass=\"int-message\">\n  <ph otherprops=\"reboxetine\" outputclass=\"int-heading-drug\">Reboxetine</ph> <ph outputclass=\"int-effectQualifier\">is predicted to</ph> <ph outputclass=\"int-effect\">increase</ph> <ph outputclass=\"int-parameter\">the risk of a hypertensive crisis when given with</ph> <ph otherprops=\"isocarboxazid\" outputclass=\"int-drug\">isocarboxazid</ph>. <ph outputclass=\"int-action\">Manufacturer advises avoid</ph>.  </p>"
							},
							"hasEvidence": "Theoretical",
							"hasImportance": "Severe",
							"hasOrder": "1",
							"hasTextContent": "Reboxetine   is predicted to   increase   the risk of a hypertensive crisis when given with   isocarboxazid .  Manufacturer advises avoid .    \n\n"
						}
					],
					"hasOrder": "19",
					"hasTitle": {
						"@type": "rdf:XMLLiteral",
						"@value": "<title>Isocarboxazid</title>"
					}
				},
				{
					"@id": "http://bnf.nice.org.uk/interaction/reboxetine-2#bnf_i1643858009527",
					"hasMessage": [
						{
							"@id": "http://bnf.nice.org.uk/interaction/reboxetine-2#bnf_i1643858009527_message_0",
							"hasDitaContent": {
								"@type": "rdf:XMLLiteral",
								"@value": "<p otherprops=\"Moderate\" outputclass=\"int-message\">\n  <ph otherprops=\"itraconazole\" outputclass=\"int-drug\">Itraconazole</ph> <ph outputclass=\"int-effectQualifier\">is predicted to</ph> <ph outputclass=\"int-effect\">increase</ph> <ph outputclass=\"int-parameter\">the exposure to</ph> <ph otherprops=\"reboxetine\" outputclass=\"int-heading-drug\">reboxetine</ph>. <ph outputclass=\"int-action\">Manufacturer advises avoid</ph>.  </p>"
							},
							"hasEvidence": "Study",
							"hasImportance": "Moderate",
							"hasOrder": "1",
							"hasTextContent": "Itraconazole   is predicted to   increase   the exposure to   reboxetine .  Manufacturer advises avoid .    \n\n"
						}
					],
					"hasOrder": "20",
					"hasTitle": {
						"@type": "rdf:XMLLiteral",
						"@value": "<title>Itraconazole</title>"
					}
				},
				{
					"@id": "http://bnf.nice.org.uk/interaction/reboxetine-2#bnf_i1643858009528",
					"hasMessage": [
						{
							"@id": "http://bnf.nice.org.uk/interaction/reboxetine-2#bnf_i1643858009528_message_0",
							"hasDitaContent": {
								"@type": "rdf:XMLLiteral",
								"@value": "<p otherprops=\"Moderate\" outputclass=\"int-message\">\n  <ph otherprops=\"ketoconazole\" outputclass=\"int-drug\">Ketoconazole</ph> <ph outputclass=\"int-effectQualifier\">is predicted to</ph> <ph outputclass=\"int-effect\">increase</ph> <ph outputclass=\"int-parameter\">the exposure to</ph> <ph otherprops=\"reboxetine\" outputclass=\"int-heading-drug\">reboxetine</ph>. <ph outputclass=\"int-action\">Manufacturer advises avoid</ph>.  </p>"
							},
							"hasEvidence": "Study",
							"hasImportance": "Moderate",
							"hasOrder": "1",
							"hasTextContent": "Ketoconazole   is predicted to   increase   the exposure to   reboxetine .  Manufacturer advises avoid .    \n\n"
						}
					],
					"hasOrder": "21",
					"hasTitle": {
						"@type": "rdf:XMLLiteral",
						"@value": "<title>Ketoconazole</title>"
					}
				},
				{
					"@id": "http://bnf.nice.org.uk/interaction/reboxetine-2#bnf_i1643858009529",
					"hasMessage": [
						{
							"@id": "http://bnf.nice.org.uk/interaction/reboxetine-2#bnf_i1643858009529_message_0",
							"hasDitaContent": {
								"@type": "rdf:XMLLiteral",
								"@value": "<p otherprops=\"Severe\" outputclass=\"int-message\">\n  <ph otherprops=\"reboxetine\" outputclass=\"int-heading-drug\">Reboxetine</ph> <ph outputclass=\"int-effectQualifier\">is predicted to</ph> <ph outputclass=\"int-effect\">increase</ph> <ph outputclass=\"int-parameter\">the risk of a hypertensive crisis when given with</ph> <ph otherprops=\"linezolid\" outputclass=\"int-drug\">linezolid</ph>. <ph outputclass=\"int-action\">Manufacturer advises avoid</ph>.  </p>"
							},
							"hasEvidence": "Theoretical",
							"hasImportance": "Severe",
							"hasOrder": "1",
							"hasTextContent": "Reboxetine   is predicted to   increase   the risk of a hypertensive crisis when given with   linezolid .  Manufacturer advises avoid .    \n\n"
						}
					],
					"hasOrder": "22",
					"hasTitle": {
						"@type": "rdf:XMLLiteral",
						"@value": "<title>Linezolid</title>"
					}
				},
				{
					"@id": "http://bnf.nice.org.uk/interaction/reboxetine-2#bnf_i1643858009530",
					"hasMessage": [
						{
							"@id": "http://bnf.nice.org.uk/interaction/reboxetine-2#bnf_i1643858009530_message_0",
							"hasDitaContent": {
								"@type": "rdf:XMLLiteral",
								"@value": "<p otherprops=\"Moderate\" outputclass=\"int-message\">\n  <ph otherprops=\"lopinavir\" outputclass=\"int-drug\">Lopinavir</ph> <ph outputclass=\"int-effectQualifier\">is predicted to</ph> <ph outputclass=\"int-effect\">increase</ph> <ph outputclass=\"int-parameter\">the exposure to</ph> <ph otherprops=\"reboxetine\" outputclass=\"int-heading-drug\">reboxetine</ph>. <ph outputclass=\"int-action\">Manufacturer advises avoid</ph>.  </p>"
							},
							"hasEvidence": "Study",
							"hasImportance": "Moderate",
							"hasOrder": "1",
							"hasTextContent": "Lopinavir   is predicted to   increase   the exposure to   reboxetine .  Manufacturer advises avoid .    \n\n"
						}
					],
					"hasOrder": "23",
					"hasTitle": {
						"@type": "rdf:XMLLiteral",
						"@value": "<title>Lopinavir</title>"
					}
				},
				{
					"@id": "http://bnf.nice.org.uk/interaction/reboxetine-2#bnf_i1643858009531",
					"hasMessage": [
						{
							"@id": "http://bnf.nice.org.uk/interaction/reboxetine-2#bnf_i1643858009531_message_0",
							"hasDitaContent": {
								"@type": "rdf:XMLLiteral",
								"@value": "<p otherprops=\"Moderate\" outputclass=\"int-message\">\n  <ph otherprops=\"reboxetine\" outputclass=\"int-heading-drug\">Reboxetine</ph> <ph outputclass=\"int-effectQualifier\">is predicted to</ph> <ph outputclass=\"int-effect\">increase</ph> <ph outputclass=\"int-parameter\">the risk of hypokalaemia when given with</ph> <ph otherprops=\"metolazone\" outputclass=\"int-drug\">metolazone</ph>. <ph outputclass=\"int-action\">Manufacturer makes no recommendation</ph>.  </p>"
							},
							"hasEvidence": "Anecdotal",
							"hasImportance": "Moderate",
							"hasOrder": "1",
							"hasTextContent": "Reboxetine   is predicted to   increase   the risk of hypokalaemia when given with   metolazone .  Manufacturer makes no recommendation .    \n\n"
						}
					],
					"hasOrder": "24",
					"hasTitle": {
						"@type": "rdf:XMLLiteral",
						"@value": "<title>Metolazone</title>"
					}
				},
				{
					"@id": "http://bnf.nice.org.uk/interaction/reboxetine-2#bnf_i1643858009532",
					"hasMessage": [
						{
							"@id": "http://bnf.nice.org.uk/interaction/reboxetine-2#bnf_i1643858009532_message_0",
							"hasDitaContent": {
								"@type": "rdf:XMLLiteral",
								"@value": "<p otherprops=\"Moderate\" outputclass=\"int-message\">\n  <ph otherprops=\"miconazole\" outputclass=\"int-drug\">Miconazole</ph> <ph outputclass=\"int-effectQualifier\">is predicted to</ph> <ph outputclass=\"int-effect\">increase</ph> <ph outputclass=\"int-parameter\">the concentration of</ph> <ph otherprops=\"reboxetine\" outputclass=\"int-heading-drug\">reboxetine</ph>. <ph outputclass=\"int-action\">Manufacturer advises use with caution and adjust dose</ph>.  </p>"
							},
							"hasEvidence": "Theoretical",
							"hasImportance": "Moderate",
							"hasOrder": "1",
							"hasTextContent": "Miconazole   is predicted to   increase   the concentration of   reboxetine .  Manufacturer advises use with caution and adjust dose .    \n\n"
						}
					],
					"hasOrder": "25",
					"hasTitle": {
						"@type": "rdf:XMLLiteral",
						"@value": "<title>Miconazole</title>"
					}
				},
				{
					"@id": "http://bnf.nice.org.uk/interaction/reboxetine-2#bnf_i1643858009533",
					"hasMessage": [
						{
							"@id": "http://bnf.nice.org.uk/interaction/reboxetine-2#bnf_i1643858009533_message_0",
							"hasDitaContent": {
								"@type": "rdf:XMLLiteral",
								"@value": "<p otherprops=\"Moderate\" outputclass=\"int-message\">\n  <ph otherprops=\"mitotane\" outputclass=\"int-drug\">Mitotane</ph> <ph outputclass=\"int-effectQualifier\">is predicted to</ph> <ph outputclass=\"int-effect\">decrease</ph> <ph outputclass=\"int-parameter\">the exposure to</ph> <ph otherprops=\"reboxetine\" outputclass=\"int-heading-drug\">reboxetine</ph>. <ph outputclass=\"int-action\">Manufacturer makes no recommendation</ph>.  </p>"
							},
							"hasEvidence": "Anecdotal",
							"hasImportance": "Moderate",
							"hasOrder": "1",
							"hasTextContent": "Mitotane   is predicted to   decrease   the exposure to   reboxetine .  Manufacturer makes no recommendation .    \n\n"
						}
					],
					"hasOrder": "26",
					"hasTitle": {
						"@type": "rdf:XMLLiteral",
						"@value": "<title>Mitotane</title>"
					}
				},
				{
					"@id": "http://bnf.nice.org.uk/interaction/reboxetine-2#bnf_i1643858009534",
					"hasMessage": [
						{
							"@id": "http://bnf.nice.org.uk/interaction/reboxetine-2#bnf_i1643858009534_message_0",
							"hasDitaContent": {
								"@type": "rdf:XMLLiteral",
								"@value": "<p otherprops=\"Severe\" outputclass=\"int-message\">\n  <ph otherprops=\"reboxetine\" outputclass=\"int-heading-drug\">Reboxetine</ph> <ph outputclass=\"int-effectQualifier\">is predicted to</ph> <ph outputclass=\"int-effect\">increase</ph> <ph outputclass=\"int-parameter\">the risk of a hypertensive crisis when given with</ph> <ph otherprops=\"moclobemide\" outputclass=\"int-drug\">moclobemide</ph>. <ph outputclass=\"int-action\">Manufacturer advises avoid</ph>.  </p>"
							},
							"hasEvidence": "Theoretical",
							"hasImportance": "Severe",
							"hasOrder": "1",
							"hasTextContent": "Reboxetine   is predicted to   increase   the risk of a hypertensive crisis when given with   moclobemide .  Manufacturer advises avoid .    \n\n"
						}
					],
					"hasOrder": "27",
					"hasTitle": {
						"@type": "rdf:XMLLiteral",
						"@value": "<title>Moclobemide</title>"
					}
				},
				{
					"@id": "http://bnf.nice.org.uk/interaction/reboxetine-2#bnf_i1643858009535",
					"hasMessage": [
						{
							"@id": "http://bnf.nice.org.uk/interaction/reboxetine-2#bnf_i1643858009535_message_0",
							"hasDitaContent": {
								"@type": "rdf:XMLLiteral",
								"@value": "<p otherprops=\"Severe\" outputclass=\"int-message\">\n  <ph otherprops=\"reboxetine\" outputclass=\"int-heading-drug\">Reboxetine</ph> <ph outputclass=\"int-effectQualifier\">is predicted to</ph> <ph outputclass=\"int-effect\">increase</ph> <ph outputclass=\"int-parameter\">the risk of a hypertensive crisis when given with</ph> <ph otherprops=\"phenelzine\" outputclass=\"int-drug\">phenelzine</ph>. <ph outputclass=\"int-action\">Manufacturer advises avoid</ph>.  </p>"
							},
							"hasEvidence": "Theoretical",
							"hasImportance": "Severe",
							"hasOrder": "1",
							"hasTextContent": "Reboxetine   is predicted to   increase   the risk of a hypertensive crisis when given with   phenelzine .  Manufacturer advises avoid .    \n\n"
						}
					],
					"hasOrder": "28",
					"hasTitle": {
						"@type": "rdf:XMLLiteral",
						"@value": "<title>Phenelzine</title>"
					}
				},
				{
					"@id": "http://bnf.nice.org.uk/interaction/reboxetine-2#bnf_i1643858009536",
					"hasMessage": [
						{
							"@id": "http://bnf.nice.org.uk/interaction/reboxetine-2#bnf_i1643858009536_message_0",
							"hasDitaContent": {
								"@type": "rdf:XMLLiteral",
								"@value": "<p otherprops=\"Moderate\" outputclass=\"int-message\">\n  <ph otherprops=\"phenobarbital\" outputclass=\"int-drug\">Phenobarbital</ph> <ph outputclass=\"int-effectQualifier\">is predicted to</ph> <ph outputclass=\"int-effect\">decrease</ph> <ph outputclass=\"int-parameter\">the exposure to</ph> <ph otherprops=\"reboxetine\" outputclass=\"int-heading-drug\">reboxetine</ph>. <ph outputclass=\"int-action\">Manufacturer makes no recommendation</ph>.  </p>"
							},
							"hasEvidence": "Anecdotal",
							"hasImportance": "Moderate",
							"hasOrder": "1",
							"hasTextContent": "Phenobarbital   is predicted to   decrease   the exposure to   reboxetine .  Manufacturer makes no recommendation .    \n\n"
						}
					],
					"hasOrder": "29",
					"hasTitle": {
						"@type": "rdf:XMLLiteral",
						"@value": "<title>Phenobarbital</title>"
					}
				},
				{
					"@id": "http://bnf.nice.org.uk/interaction/reboxetine-2#bnf_i1643858009537",
					"hasMessage": [
						{
							"@id": "http://bnf.nice.org.uk/interaction/reboxetine-2#bnf_i1643858009537_message_0",
							"hasDitaContent": {
								"@type": "rdf:XMLLiteral",
								"@value": "<p otherprops=\"Moderate\" outputclass=\"int-message\">\n  <ph otherprops=\"phenytoin\" outputclass=\"int-drug\">Phenytoin</ph> <ph outputclass=\"int-effectQualifier\">is predicted to</ph> <ph outputclass=\"int-effect\">decrease</ph> <ph outputclass=\"int-parameter\">the exposure to</ph> <ph otherprops=\"reboxetine\" outputclass=\"int-heading-drug\">reboxetine</ph>. <ph outputclass=\"int-action\">Manufacturer makes no recommendation</ph>.  </p>"
							},
							"hasEvidence": "Anecdotal",
							"hasImportance": "Moderate",
							"hasOrder": "1",
							"hasTextContent": "Phenytoin   is predicted to   decrease   the exposure to   reboxetine .  Manufacturer makes no recommendation .    \n\n"
						}
					],
					"hasOrder": "30",
					"hasTitle": {
						"@type": "rdf:XMLLiteral",
						"@value": "<title>Phenytoin</title>"
					}
				},
				{
					"@id": "http://bnf.nice.org.uk/interaction/reboxetine-2#bnf_i1643858009538",
					"hasMessage": [
						{
							"@id": "http://bnf.nice.org.uk/interaction/reboxetine-2#bnf_i1643858009538_message_0",
							"hasDitaContent": {
								"@type": "rdf:XMLLiteral",
								"@value": "<p otherprops=\"Moderate\" outputclass=\"int-message\">\n  <ph otherprops=\"primidone\" outputclass=\"int-drug\">Primidone</ph> <ph outputclass=\"int-effectQualifier\">is predicted to</ph> <ph outputclass=\"int-effect\">decrease</ph> <ph outputclass=\"int-parameter\">the exposure to</ph> <ph otherprops=\"reboxetine\" outputclass=\"int-heading-drug\">reboxetine</ph>. <ph outputclass=\"int-action\">Manufacturer makes no recommendation</ph>.  </p>"
							},
							"hasEvidence": "Anecdotal",
							"hasImportance": "Moderate",
							"hasOrder": "1",
							"hasTextContent": "Primidone   is predicted to   decrease   the exposure to   reboxetine .  Manufacturer makes no recommendation .    \n\n"
						}
					],
					"hasOrder": "31",
					"hasTitle": {
						"@type": "rdf:XMLLiteral",
						"@value": "<title>Primidone</title>"
					}
				},
				{
					"@id": "http://bnf.nice.org.uk/interaction/reboxetine-2#bnf_i1643858009539",
					"hasMessage": [
						{
							"@id": "http://bnf.nice.org.uk/interaction/reboxetine-2#bnf_i1643858009539_message_0",
							"hasDitaContent": {
								"@type": "rdf:XMLLiteral",
								"@value": "<p otherprops=\"Severe\" outputclass=\"int-message\">\n  <ph otherprops=\"reboxetine\" outputclass=\"int-heading-drug\">Reboxetine</ph> <ph outputclass=\"int-effectQualifier\">is predicted to</ph> <ph outputclass=\"int-effect\">increase</ph> <ph outputclass=\"int-parameter\">the risk of a hypertensive crisis when given with</ph> <ph otherprops=\"rasagiline\" outputclass=\"int-drug\">rasagiline</ph>. <ph outputclass=\"int-action\">Manufacturer advises avoid</ph>.  </p>"
							},
							"hasEvidence": "Theoretical",
							"hasImportance": "Severe",
							"hasOrder": "1",
							"hasTextContent": "Reboxetine   is predicted to   increase   the risk of a hypertensive crisis when given with   rasagiline .  Manufacturer advises avoid .    \n\n"
						}
					],
					"hasOrder": "32",
					"hasTitle": {
						"@type": "rdf:XMLLiteral",
						"@value": "<title>Rasagiline</title>"
					}
				},
				{
					"@id": "http://bnf.nice.org.uk/interaction/reboxetine-2#bnf_i1643858009540",
					"hasMessage": [
						{
							"@id": "http://bnf.nice.org.uk/interaction/reboxetine-2#bnf_i1643858009540_message_0",
							"hasDitaContent": {
								"@type": "rdf:XMLLiteral",
								"@value": "<p otherprops=\"Moderate\" outputclass=\"int-message\">\n  <ph otherprops=\"rifampicin\" outputclass=\"int-drug\">Rifampicin</ph> <ph outputclass=\"int-effectQualifier\">is predicted to</ph> <ph outputclass=\"int-effect\">decrease</ph> <ph outputclass=\"int-parameter\">the exposure to</ph> <ph otherprops=\"reboxetine\" outputclass=\"int-heading-drug\">reboxetine</ph>. <ph outputclass=\"int-action\">Manufacturer makes no recommendation</ph>.  </p>"
							},
							"hasEvidence": "Anecdotal",
							"hasImportance": "Moderate",
							"hasOrder": "1",
							"hasTextContent": "Rifampicin   is predicted to   decrease   the exposure to   reboxetine .  Manufacturer makes no recommendation .    \n\n"
						}
					],
					"hasOrder": "33",
					"hasTitle": {
						"@type": "rdf:XMLLiteral",
						"@value": "<title>Rifampicin</title>"
					}
				},
				{
					"@id": "http://bnf.nice.org.uk/interaction/reboxetine-2#bnf_i1643858009541",
					"hasMessage": [
						{
							"@id": "http://bnf.nice.org.uk/interaction/reboxetine-2#bnf_i1643858009541_message_0",
							"hasDitaContent": {
								"@type": "rdf:XMLLiteral",
								"@value": "<p otherprops=\"Moderate\" outputclass=\"int-message\">\n  <ph otherprops=\"ritonavir\" outputclass=\"int-drug\">Ritonavir</ph> <ph outputclass=\"int-effectQualifier\">is predicted to</ph> <ph outputclass=\"int-effect\">increase</ph> <ph outputclass=\"int-parameter\">the exposure to</ph> <ph otherprops=\"reboxetine\" outputclass=\"int-heading-drug\">reboxetine</ph>. <ph outputclass=\"int-action\">Manufacturer advises avoid</ph>.  </p>"
							},
							"hasEvidence": "Study",
							"hasImportance": "Moderate",
							"hasOrder": "1",
							"hasTextContent": "Ritonavir   is predicted to   increase   the exposure to   reboxetine .  Manufacturer advises avoid .    \n\n"
						}
					],
					"hasOrder": "34",
					"hasTitle": {
						"@type": "rdf:XMLLiteral",
						"@value": "<title>Ritonavir</title>"
					}
				},
				{
					"@id": "http://bnf.nice.org.uk/interaction/reboxetine-2#bnf_i1643858009542",
					"hasMessage": [
						{
							"@id": "http://bnf.nice.org.uk/interaction/reboxetine-2#bnf_i1643858009542_message_0",
							"hasDitaContent": {
								"@type": "rdf:XMLLiteral",
								"@value": "<p otherprops=\"Severe\" outputclass=\"int-message\">\n  <ph otherprops=\"reboxetine\" outputclass=\"int-heading-drug\">Reboxetine</ph> <ph outputclass=\"int-effectQualifier\">is predicted to</ph> <ph outputclass=\"int-effect\">increase</ph> <ph outputclass=\"int-parameter\">the risk of a hypertensive crisis when given with</ph> <ph otherprops=\"selegiline\" outputclass=\"int-drug\">selegiline</ph>. <ph outputclass=\"int-action\">Manufacturer advises avoid</ph>.  </p>"
							},
							"hasEvidence": "Theoretical",
							"hasImportance": "Severe",
							"hasOrder": "1",
							"hasTextContent": "Reboxetine   is predicted to   increase   the risk of a hypertensive crisis when given with   selegiline .  Manufacturer advises avoid .    \n\n"
						}
					],
					"hasOrder": "35",
					"hasTitle": {
						"@type": "rdf:XMLLiteral",
						"@value": "<title>Selegiline</title>"
					}
				},
				{
					"@id": "http://bnf.nice.org.uk/interaction/reboxetine-2#bnf_i1643858009543",
					"hasMessage": [
						{
							"@id": "http://bnf.nice.org.uk/interaction/reboxetine-2#bnf_i1643858009543_message_0",
							"hasDitaContent": {
								"@type": "rdf:XMLLiteral",
								"@value": "<p otherprops=\"Moderate\" outputclass=\"int-message\">\n  <ph otherprops=\"tipranavir\" outputclass=\"int-drug\">Tipranavir</ph> <ph outputclass=\"int-effectQualifier\">is predicted to</ph> <ph outputclass=\"int-effect\">increase</ph> <ph outputclass=\"int-parameter\">the exposure to</ph> <ph otherprops=\"reboxetine\" outputclass=\"int-heading-drug\">reboxetine</ph>. <ph outputclass=\"int-action\">Manufacturer advises avoid</ph>.  </p>"
							},
							"hasEvidence": "Study",
							"hasImportance": "Moderate",
							"hasOrder": "1",
							"hasTextContent": "Tipranavir   is predicted to   increase   the exposure to   reboxetine .  Manufacturer advises avoid .    \n\n"
						}
					],
					"hasOrder": "36",
					"hasTitle": {
						"@type": "rdf:XMLLiteral",
						"@value": "<title>Tipranavir</title>"
					}
				},
				{
					"@id": "http://bnf.nice.org.uk/interaction/reboxetine-2#bnf_i1643858009544",
					"hasMessage": [
						{
							"@id": "http://bnf.nice.org.uk/interaction/reboxetine-2#bnf_i1643858009544_message_0",
							"hasDitaContent": {
								"@type": "rdf:XMLLiteral",
								"@value": "<p otherprops=\"Moderate\" outputclass=\"int-message\">\n  <ph otherprops=\"reboxetine\" outputclass=\"int-heading-drug\">Reboxetine</ph> <ph outputclass=\"int-effectQualifier\">is predicted to</ph> <ph outputclass=\"int-effect\">increase</ph> <ph outputclass=\"int-parameter\">the risk of hypokalaemia when given with</ph> <ph otherprops=\"torasemide\" outputclass=\"int-drug\">torasemide</ph>. <ph outputclass=\"int-action\">Manufacturer makes no recommendation</ph>.  </p>"
							},
							"hasEvidence": "Theoretical",
							"hasImportance": "Moderate",
							"hasOrder": "1",
							"hasTextContent": "Reboxetine   is predicted to   increase   the risk of hypokalaemia when given with   torasemide .  Manufacturer makes no recommendation .    \n\n"
						}
					],
					"hasOrder": "37",
					"hasTitle": {
						"@type": "rdf:XMLLiteral",
						"@value": "<title>Torasemide</title>"
					}
				},
				{
					"@id": "http://bnf.nice.org.uk/interaction/reboxetine-2#bnf_i1643858009545",
					"hasMessage": [
						{
							"@id": "http://bnf.nice.org.uk/interaction/reboxetine-2#bnf_i1643858009545_message_0",
							"hasDitaContent": {
								"@type": "rdf:XMLLiteral",
								"@value": "<p otherprops=\"Severe\" outputclass=\"int-message\">\n  <ph otherprops=\"reboxetine\" outputclass=\"int-heading-drug\">Reboxetine</ph> <ph outputclass=\"int-effectQualifier\">is predicted to</ph> <ph outputclass=\"int-effect\">increase</ph> <ph outputclass=\"int-parameter\">the risk of a hypertensive crisis when given with</ph> <ph otherprops=\"tranylcypromine\" outputclass=\"int-drug\">tranylcypromine</ph>. <ph outputclass=\"int-action\">Manufacturer advises avoid</ph>.  </p>"
							},
							"hasEvidence": "Theoretical",
							"hasImportance": "Severe",
							"hasOrder": "1",
							"hasTextContent": "Reboxetine   is predicted to   increase   the risk of a hypertensive crisis when given with   tranylcypromine .  Manufacturer advises avoid .    \n\n"
						}
					],
					"hasOrder": "38",
					"hasTitle": {
						"@type": "rdf:XMLLiteral",
						"@value": "<title>Tranylcypromine</title>"
					}
				},
				{
					"@id": "http://bnf.nice.org.uk/interaction/reboxetine-2#bnf_i1643858009546",
					"hasMessage": [
						{
							"@id": "http://bnf.nice.org.uk/interaction/reboxetine-2#bnf_i1643858009546_message_0",
							"hasDitaContent": {
								"@type": "rdf:XMLLiteral",
								"@value": "<p otherprops=\"Moderate\" outputclass=\"int-message\">\n  <ph otherprops=\"voriconazole\" outputclass=\"int-drug\">Voriconazole</ph> <ph outputclass=\"int-effectQualifier\">is predicted to</ph> <ph outputclass=\"int-effect\">increase</ph> <ph outputclass=\"int-parameter\">the exposure to</ph> <ph otherprops=\"reboxetine\" outputclass=\"int-heading-drug\">reboxetine</ph>. <ph outputclass=\"int-action\">Manufacturer advises avoid</ph>.  </p>"
							},
							"hasEvidence": "Study",
							"hasImportance": "Moderate",
							"hasOrder": "1",
							"hasTextContent": "Voriconazole   is predicted to   increase   the exposure to   reboxetine .  Manufacturer advises avoid .    \n\n"
						}
					],
					"hasOrder": "39",
					"hasTitle": {
						"@type": "rdf:XMLLiteral",
						"@value": "<title>Voriconazole</title>"
					}
				},
				{
					"@id": "http://bnf.nice.org.uk/interaction/reboxetine-2#bnf_i1643858009547",
					"hasMessage": [
						{
							"@id": "http://bnf.nice.org.uk/interaction/reboxetine-2#bnf_i1643858009547_message_0",
							"hasDitaContent": {
								"@type": "rdf:XMLLiteral",
								"@value": "<p otherprops=\"Moderate\" outputclass=\"int-message\">\n  <ph otherprops=\"reboxetine\" outputclass=\"int-heading-drug\">Reboxetine</ph> <ph outputclass=\"int-effectQualifier\">is predicted to</ph> <ph outputclass=\"int-effect\">increase</ph> <ph outputclass=\"int-parameter\">the risk of hypokalaemia when given with</ph> <ph otherprops=\"xipamide\" outputclass=\"int-drug\">xipamide</ph>. <ph outputclass=\"int-action\">Manufacturer makes no recommendation</ph>.  </p>"
							},
							"hasEvidence": "Anecdotal",
							"hasImportance": "Moderate",
							"hasOrder": "1",
							"hasTextContent": "Reboxetine   is predicted to   increase   the risk of hypokalaemia when given with   xipamide .  Manufacturer makes no recommendation .    \n\n"
						}
					],
					"hasOrder": "40",
					"hasTitle": {
						"@type": "rdf:XMLLiteral",
						"@value": "<title>Xipamide</title>"
					}
				}
			],
			"hasSearchLabel": " Reboxetine  | Interactions",
			"hasSearchLink": {
				"@id": "http://bnf.nice.org.uk/interaction/reboxetine-2.html"
			},
			"hasTitle": {
				"@type": "rdf:XMLLiteral",
				"@value": "<title> Reboxetine </title>"
			},
			"rdfs:label": "reboxetine"
		}
	]
}